sef_agents/__init__.py
sef_agents/api_keys.json.example
sef_agents/auth.py
sef_agents/constants.py
sef_agents/security_scan.py
sef_agents/server.py
sef_agents/session.py
sef_agents/config/ai_patterns.yaml
sef_agents/config/frameworks/angular.yaml
sef_agents/config/frameworks/react.yaml
sef_agents/config/frameworks/spring_boot.yaml
sef_agents/config/languages/java.yaml
sef_agents/config/languages/javascript.yaml
sef_agents/config/languages/python.yaml
sef_agents/config/languages/typescript.yaml
sef_agents/core/__init__.py
sef_agents/core/config_loader.py
sef_agents/core/language_detector.py
sef_agents/models/__init__.py
sef_agents/models/gherkin.py
sef_agents/models/hierarchy.py
sef_agents/models/invest.py
sef_agents/models/version.py
sef_agents/prompts/__init__.py
sef_agents/prompts/start_agent.py
sef_agents/rules/architecture/backend_patterns.md
sef_agents/rules/architecture/diagramming.md
sef_agents/rules/architecture/frontend_patterns.md
sef_agents/rules/architecture/mermaid_templates.md
sef_agents/rules/architecture/regression_protocol.md
sef_agents/rules/architecture/system_design.md
sef_agents/rules/common/codemap_standard.md
sef_agents/rules/common/core_protocol.md
sef_agents/rules/common/prompt_engineering.md
sef_agents/rules/development/debugging.md
sef_agents/rules/development/implementation.md
sef_agents/rules/operations/completion.md
sef_agents/rules/operations/discovery.md
sef_agents/rules/operations/fix_workflow.md
sef_agents/rules/operations/forensics.md
sef_agents/rules/operations/platform.md
sef_agents/rules/operations/synchronous_flow.md
sef_agents/rules/product/ac_validation.md
sef_agents/rules/product/brainstorming.md
sef_agents/rules/product/requirements_std.md
sef_agents/rules/product/sef_flow.md
sef_agents/rules/product/strategy.md
sef_agents/rules/quality/defect_prevention.md
sef_agents/rules/quality/documentation_standards.md
sef_agents/rules/quality/qa_lead.md
sef_agents/rules/quality/test_design.md
sef_agents-0.2.0.dist-info/METADATA
sef_agents-0.2.0.dist-info/WHEEL
sef_agents-0.2.0.dist-info/entry_points.txt
sef_agents-0.2.0.dist-info/RECORD
