Metadata-Version: 2.4
Name: sef-agents
Version: 0.2.0
Summary: SEF Agents — AI-powered guidance for the Synchronous Engineering Framework. Built on Model Context Protocol (MCP).
Project-URL: Homepage, https://github.com/Mishtert/sef-agents
Project-URL: Repository, https://github.com/Mishtert/sef-agents
Author: SEF Agents Contributors
License: MIT
Requires-Python: >=3.12
Requires-Dist: fastmcp>=2.14.1
Requires-Dist: mcp>=1.25.0
Requires-Dist: networkx>=3.4
Requires-Dist: pydantic>=2.12.5
Requires-Dist: pytest>=9.0.2
Requires-Dist: structlog>=25.5.0
Requires-Dist: tree-sitter-typescript>=0.21.0
Requires-Dist: tree-sitter>=0.21.0
